parametrix/__init__.py
parametrix/py.typed
parametrix-0.1.3.dist-info/licenses/LICENSE.txt
parametrix-0.1.3.dist-info/WHEEL
parametrix-0.1.3.dist-info/METADATA
parametrix-0.1.3.dist-info/RECORD
